README.md
setup.cfg
setup.py
mrbias/__init__.py
mrbias/curve_fitting.py
mrbias/image_sets.py
mrbias/misc_utils.py
mrbias/mri_bias.py
mrbias/phantom_reference.py
mrbias/roi_detect.py
mrbias/scan_session.py
mrbias.egg-info/PKG-INFO
mrbias.egg-info/SOURCES.txt
mrbias.egg-info/dependency_links.txt
mrbias.egg-info/requires.txt
mrbias.egg-info/top_level.txt
mrbias/roi_detection_templates/siemens_skyra_3p0T/default_T1_rois.yaml
mrbias/roi_detection_templates/siemens_skyra_3p0T/default_T1_rois_4mm.yaml
mrbias/roi_detection_templates/siemens_skyra_3p0T/default_T2_rois.yaml
mrbias/roi_detection_templates/siemens_skyra_3p0T/default_T2_rois_4mm.yaml
mrbias/roi_detection_templates/siemens_skyra_3p0T/dicom/I1000000
mrbias/roi_detection_templates/siemens_skyra_3p0T/dicom/I1000001
mrbias/roi_detection_templates/siemens_skyra_3p0T/dicom/I1000002
mrbias/roi_detection_templates/siemens_skyra_3p0T/dicom/I1010000
mrbias/roi_detection_templates/siemens_skyra_3p0T/dicom/I1020000
mrbias/roi_detection_templates/siemens_skyra_3p0T/dicom/I1030000
mrbias/roi_detection_templates/siemens_skyra_3p0T/dicom/I1040000
mrbias/roi_detection_templates/siemens_skyra_3p0T/dicom/I1050000
mrbias/roi_detection_templates/siemens_skyra_3p0T/dicom/I1060000
mrbias/roi_detection_templates/siemens_skyra_3p0T/dicom/I1070000
mrbias/roi_detection_templates/siemens_skyra_3p0T/dicom/I1080000
mrbias/roi_detection_templates/siemens_skyra_3p0T/dicom/I1090000
mrbias/roi_detection_templates/siemens_skyra_3p0T/dicom/I1100000
mrbias/roi_detection_templates/siemens_skyra_3p0T/dicom/I1100001
mrbias/roi_detection_templates/siemens_skyra_3p0T/dicom/I1110000
mrbias/roi_detection_templates/siemens_skyra_3p0T/dicom/I1120000
mrbias/roi_detection_templates/siemens_skyra_3p0T/dicom/I1130000
mrbias/roi_detection_templates/siemens_skyra_3p0T/dicom/I1140000
mrbias/roi_detection_templates/siemens_skyra_3p0T/dicom/I1150000
mrbias/roi_detection_templates/siemens_skyra_3p0T/dicom/I1160000
mrbias/roi_detection_templates/siemens_skyra_3p0T/dicom/I1170000
mrbias/roi_detection_templates/siemens_skyra_3p0T/dicom/I1180000
mrbias/roi_detection_templates/siemens_skyra_3p0T/dicom/I1190000
